{
  "generatedAt": "2026-04-19T19:59:23.961Z",
  "currency": "JPY",
  "fx": {
    "baseCurrency": "JPY",
    "displayCurrencies": [
      "JPY",
      "EUR"
    ],
    "rates": {
      "JPY_PER_EUR": 187.72,
      "EUR_PER_JPY": 0.005327082889409759
    },
    "source": {
      "provider": "European Central Bank",
      "publishedDate": "2026-04-17",
      "sourceUrl": "https://www.ecb.europa.eu/stats/policy_and_exchange_rates/euro_reference_exchange_rates/html/index.en.html",
      "notes": "ECB euro foreign exchange reference rate for 17 April 2026: 1 EUR = 187.72 JPY."
    }
  },
  "tripWindow": {
    "start": "2026-03-25",
    "end": "2026-04-11",
    "days": 18
  },
  "summary": {
    "totalSpendJPY": 1857390,
    "purchaseSpendJPY": 1827170,
    "trackedTransactionCount": 107,
    "physicalCashJPY": 30220,
    "physicalCashCount": 1,
    "excludedOutflowJPY": 334377,
    "reviewCount": 0,
    "averagePerDayJPY": 103188,
    "manualExpenseCount": 9
  },
  "categoryTotals": [
    {
      "category": "flights",
      "label": "Flights",
      "group": "Transport",
      "totalJPY": 957881,
      "count": 2,
      "percentOfTotalSpend": 0.5157134473643122
    },
    {
      "category": "lodging",
      "label": "Lodging",
      "group": "Lodging",
      "totalJPY": 456375,
      "count": 9,
      "percentOfTotalSpend": 0.24570768659247655
    },
    {
      "category": "local-transit",
      "label": "Local Transit",
      "group": "Transport",
      "totalJPY": 140855,
      "count": 6,
      "percentOfTotalSpend": 0.07583490812376507
    },
    {
      "category": "general-shopping",
      "label": "General Shopping",
      "group": "Shopping",
      "totalJPY": 97289,
      "count": 18,
      "percentOfTotalSpend": 0.05237941412412041
    },
    {
      "category": "attractions",
      "label": "Attractions",
      "group": "Activities",
      "totalJPY": 37383,
      "count": 3,
      "percentOfTotalSpend": 0.020126629302408217
    },
    {
      "category": "clothing",
      "label": "Clothing",
      "group": "Shopping",
      "totalJPY": 36034,
      "count": 4,
      "percentOfTotalSpend": 0.019400341339191017
    },
    {
      "category": "physical-cash",
      "label": "Physical Cash",
      "group": "Physical Cash",
      "totalJPY": 30220,
      "count": 1,
      "percentOfTotalSpend": 0.016270142511804198
    },
    {
      "category": "convenience-store",
      "label": "Convenience Store",
      "group": "Food & Drink",
      "totalJPY": 28960,
      "count": 33,
      "percentOfTotalSpend": 0.015591771248903031
    },
    {
      "category": "souvenirs",
      "label": "Souvenirs",
      "group": "Shopping",
      "totalJPY": 18535,
      "count": 11,
      "percentOfTotalSpend": 0.009979056633232654
    },
    {
      "category": "anime-hobby",
      "label": "Anime Hobby",
      "group": "Shopping",
      "totalJPY": 18080,
      "count": 5,
      "percentOfTotalSpend": 0.009734089232740566
    },
    {
      "category": "pharmacy-beauty",
      "label": "Pharmacy Beauty",
      "group": "Health & Beauty",
      "totalJPY": 16169,
      "count": 5,
      "percentOfTotalSpend": 0.008705226150673795
    },
    {
      "category": "food-drink",
      "label": "Food Drink",
      "group": "Food & Drink",
      "totalJPY": 9479,
      "count": 7,
      "percentOfTotalSpend": 0.0051033977786033085
    },
    {
      "category": "connectivity",
      "label": "Connectivity",
      "group": "Trip Setup",
      "totalJPY": 5400,
      "count": 1,
      "percentOfTotalSpend": 0.0029073054124335762
    },
    {
      "category": "toys",
      "label": "Toys",
      "group": "Shopping",
      "totalJPY": 4730,
      "count": 2,
      "percentOfTotalSpend": 0.0025465841853353362
    }
  ],
  "groupTotals": [
    {
      "group": "Transport",
      "totalJPY": 1098736,
      "count": 8
    },
    {
      "group": "Lodging",
      "totalJPY": 456375,
      "count": 9
    },
    {
      "group": "Shopping",
      "totalJPY": 174668,
      "count": 40
    },
    {
      "group": "Food & Drink",
      "totalJPY": 38439,
      "count": 40
    },
    {
      "group": "Activities",
      "totalJPY": 37383,
      "count": 3
    },
    {
      "group": "Physical Cash",
      "totalJPY": 30220,
      "count": 1
    },
    {
      "group": "Health & Beauty",
      "totalJPY": 16169,
      "count": 5
    },
    {
      "group": "Trip Setup",
      "totalJPY": 5400,
      "count": 1
    }
  ],
  "merchantTotals": [
    {
      "merchant": "International flights",
      "totalJPY": 915090,
      "count": 1,
      "category": "flights"
    },
    {
      "merchant": "Hotel booking",
      "totalJPY": 452705,
      "count": 6,
      "category": "lodging"
    },
    {
      "merchant": "JR Central",
      "totalJPY": 96520,
      "count": 2,
      "category": "local-transit"
    },
    {
      "merchant": "Domestic flight",
      "totalJPY": 42791,
      "count": 1,
      "category": "flights"
    },
    {
      "merchant": "BicCamera Akiba",
      "totalJPY": 36635,
      "count": 1,
      "category": "general-shopping"
    },
    {
      "merchant": "ATM cash withdrawal",
      "totalJPY": 30220,
      "count": 1,
      "category": "physical-cash"
    },
    {
      "merchant": "Klook",
      "totalJPY": 28158,
      "count": 1,
      "category": "attractions"
    },
    {
      "merchant": "Suica via Apple Pay",
      "totalJPY": 20000,
      "count": 1,
      "category": "local-transit"
    },
    {
      "merchant": "Suica",
      "totalJPY": 20000,
      "count": 2,
      "category": "local-transit"
    },
    {
      "merchant": "GU",
      "totalJPY": 16434,
      "count": 2,
      "category": "clothing"
    },
    {
      "merchant": "UNIQLO",
      "totalJPY": 12682,
      "count": 1,
      "category": "clothing"
    },
    {
      "merchant": "7-Eleven",
      "totalJPY": 12260,
      "count": 13,
      "category": "convenience-store"
    },
    {
      "merchant": "FamilyMart",
      "totalJPY": 11407,
      "count": 10,
      "category": "convenience-store"
    },
    {
      "merchant": "Don Quijote Asakusa",
      "totalJPY": 10257,
      "count": 2,
      "category": "general-shopping"
    },
    {
      "merchant": "Matsumoto Kiyoshi",
      "totalJPY": 8910,
      "count": 1,
      "category": "pharmacy-beauty"
    },
    {
      "merchant": "Daiso",
      "totalJPY": 8250,
      "count": 3,
      "category": "general-shopping"
    },
    {
      "merchant": "Magazines Ueno Hirokoji",
      "totalJPY": 8200,
      "count": 1,
      "category": "general-shopping"
    },
    {
      "merchant": "Tokyo Skytree",
      "totalJPY": 7740,
      "count": 1,
      "category": "attractions"
    },
    {
      "merchant": "Yodobashi",
      "totalJPY": 7710,
      "count": 1,
      "category": "general-shopping"
    },
    {
      "merchant": "Sugi Pharmacy",
      "totalJPY": 7259,
      "count": 4,
      "category": "pharmacy-beauty"
    }
  ],
  "dailyTotals": [
    {
      "date": "2026-03-25",
      "totalJPY": 35000,
      "count": 2
    },
    {
      "date": "2026-03-26",
      "totalJPY": 915090,
      "count": 1
    },
    {
      "date": "2026-03-27",
      "totalJPY": 103232,
      "count": 7
    },
    {
      "date": "2026-03-28",
      "totalJPY": 37883,
      "count": 6
    },
    {
      "date": "2026-03-29",
      "totalJPY": 3098,
      "count": 2
    },
    {
      "date": "2026-03-30",
      "totalJPY": 41978,
      "count": 9
    },
    {
      "date": "2026-03-31",
      "totalJPY": 138515,
      "count": 6
    },
    {
      "date": "2026-04-01",
      "totalJPY": 20719,
      "count": 5
    },
    {
      "date": "2026-04-02",
      "totalJPY": 12620,
      "count": 12
    },
    {
      "date": "2026-04-03",
      "totalJPY": 177060,
      "count": 5
    },
    {
      "date": "2026-04-04",
      "totalJPY": 1097,
      "count": 2
    },
    {
      "date": "2026-04-05",
      "totalJPY": 59497,
      "count": 8
    },
    {
      "date": "2026-04-06",
      "totalJPY": 4916,
      "count": 4
    },
    {
      "date": "2026-04-07",
      "totalJPY": 61700,
      "count": 6
    },
    {
      "date": "2026-04-08",
      "totalJPY": 13249,
      "count": 3
    },
    {
      "date": "2026-04-09",
      "totalJPY": 37250,
      "count": 4
    },
    {
      "date": "2026-04-10",
      "totalJPY": 113039,
      "count": 12
    },
    {
      "date": "2026-04-11",
      "totalJPY": 81447,
      "count": 13
    }
  ],
  "dailyCategoryTotals": [
    {
      "date": "2026-03-25",
      "category": "local-transit",
      "totalJPY": 35000,
      "count": 2
    },
    {
      "date": "2026-03-26",
      "category": "flights",
      "totalJPY": 915090,
      "count": 1
    },
    {
      "date": "2026-03-27",
      "category": "anime-hobby",
      "totalJPY": 5840,
      "count": 2
    },
    {
      "date": "2026-03-27",
      "category": "convenience-store",
      "totalJPY": 1278,
      "count": 2
    },
    {
      "date": "2026-03-27",
      "category": "food-drink",
      "totalJPY": 630,
      "count": 1
    },
    {
      "date": "2026-03-27",
      "category": "lodging",
      "totalJPY": 95484,
      "count": 2
    },
    {
      "date": "2026-03-28",
      "category": "anime-hobby",
      "totalJPY": 5000,
      "count": 2
    },
    {
      "date": "2026-03-28",
      "category": "convenience-store",
      "totalJPY": 2663,
      "count": 3
    },
    {
      "date": "2026-03-28",
      "category": "physical-cash",
      "totalJPY": 30220,
      "count": 1
    },
    {
      "date": "2026-03-29",
      "category": "convenience-store",
      "totalJPY": 757,
      "count": 1
    },
    {
      "date": "2026-03-29",
      "category": "general-shopping",
      "totalJPY": 2341,
      "count": 1
    },
    {
      "date": "2026-03-30",
      "category": "clothing",
      "totalJPY": 22546,
      "count": 2
    },
    {
      "date": "2026-03-30",
      "category": "convenience-store",
      "totalJPY": 1891,
      "count": 3
    },
    {
      "date": "2026-03-30",
      "category": "general-shopping",
      "totalJPY": 12811,
      "count": 2
    },
    {
      "date": "2026-03-30",
      "category": "toys",
      "totalJPY": 4730,
      "count": 2
    },
    {
      "date": "2026-03-31",
      "category": "anime-hobby",
      "totalJPY": 7240,
      "count": 1
    },
    {
      "date": "2026-03-31",
      "category": "convenience-store",
      "totalJPY": 949,
      "count": 2
    },
    {
      "date": "2026-03-31",
      "category": "local-transit",
      "totalJPY": 30975,
      "count": 2
    },
    {
      "date": "2026-03-31",
      "category": "lodging",
      "totalJPY": 99351,
      "count": 1
    },
    {
      "date": "2026-04-01",
      "category": "connectivity",
      "totalJPY": 5400,
      "count": 1
    },
    {
      "date": "2026-04-01",
      "category": "convenience-store",
      "totalJPY": 4499,
      "count": 1
    },
    {
      "date": "2026-04-01",
      "category": "food-drink",
      "totalJPY": 2700,
      "count": 1
    },
    {
      "date": "2026-04-01",
      "category": "general-shopping",
      "totalJPY": 4050,
      "count": 1
    },
    {
      "date": "2026-04-01",
      "category": "pharmacy-beauty",
      "totalJPY": 4070,
      "count": 1
    },
    {
      "date": "2026-04-02",
      "category": "convenience-store",
      "totalJPY": 3626,
      "count": 6
    },
    {
      "date": "2026-04-02",
      "category": "pharmacy-beauty",
      "totalJPY": 1454,
      "count": 1
    },
    {
      "date": "2026-04-02",
      "category": "souvenirs",
      "totalJPY": 7540,
      "count": 5
    },
    {
      "date": "2026-04-03",
      "category": "convenience-store",
      "totalJPY": 528,
      "count": 1
    },
    {
      "date": "2026-04-03",
      "category": "food-drink",
      "totalJPY": 4639,
      "count": 2
    },
    {
      "date": "2026-04-03",
      "category": "local-transit",
      "totalJPY": 69880,
      "count": 1
    },
    {
      "date": "2026-04-03",
      "category": "lodging",
      "totalJPY": 102013,
      "count": 1
    },
    {
      "date": "2026-04-04",
      "category": "convenience-store",
      "totalJPY": 1097,
      "count": 2
    },
    {
      "date": "2026-04-05",
      "category": "attractions",
      "totalJPY": 1485,
      "count": 1
    },
    {
      "date": "2026-04-05",
      "category": "clothing",
      "totalJPY": 6570,
      "count": 1
    },
    {
      "date": "2026-04-05",
      "category": "food-drink",
      "totalJPY": 810,
      "count": 1
    },
    {
      "date": "2026-04-05",
      "category": "general-shopping",
      "totalJPY": 5500,
      "count": 2
    },
    {
      "date": "2026-04-05",
      "category": "lodging",
      "totalJPY": 45132,
      "count": 3
    },
    {
      "date": "2026-04-06",
      "category": "convenience-store",
      "totalJPY": 416,
      "count": 1
    },
    {
      "date": "2026-04-06",
      "category": "food-drink",
      "totalJPY": 700,
      "count": 2
    },
    {
      "date": "2026-04-06",
      "category": "souvenirs",
      "totalJPY": 3800,
      "count": 1
    },
    {
      "date": "2026-04-07",
      "category": "convenience-store",
      "totalJPY": 1300,
      "count": 2
    },
    {
      "date": "2026-04-07",
      "category": "general-shopping",
      "totalJPY": 1800,
      "count": 2
    },
    {
      "date": "2026-04-07",
      "category": "local-transit",
      "totalJPY": 5000,
      "count": 1
    },
    {
      "date": "2026-04-07",
      "category": "lodging",
      "totalJPY": 53600,
      "count": 1
    },
    {
      "date": "2026-04-08",
      "category": "convenience-store",
      "totalJPY": 1534,
      "count": 1
    },
    {
      "date": "2026-04-08",
      "category": "general-shopping",
      "totalJPY": 2805,
      "count": 1
    },
    {
      "date": "2026-04-08",
      "category": "pharmacy-beauty",
      "totalJPY": 8910,
      "count": 1
    },
    {
      "date": "2026-04-09",
      "category": "attractions",
      "totalJPY": 28158,
      "count": 1
    },
    {
      "date": "2026-04-09",
      "category": "convenience-store",
      "totalJPY": 182,
      "count": 1
    },
    {
      "date": "2026-04-09",
      "category": "general-shopping",
      "totalJPY": 8910,
      "count": 2
    },
    {
      "date": "2026-04-10",
      "category": "convenience-store",
      "totalJPY": 6081,
      "count": 4
    },
    {
      "date": "2026-04-10",
      "category": "flights",
      "totalJPY": 42791,
      "count": 1
    },
    {
      "date": "2026-04-10",
      "category": "general-shopping",
      "totalJPY": 600,
      "count": 2
    },
    {
      "date": "2026-04-10",
      "category": "lodging",
      "totalJPY": 60795,
      "count": 1
    },
    {
      "date": "2026-04-10",
      "category": "pharmacy-beauty",
      "totalJPY": 657,
      "count": 1
    },
    {
      "date": "2026-04-10",
      "category": "souvenirs",
      "totalJPY": 2115,
      "count": 3
    },
    {
      "date": "2026-04-11",
      "category": "attractions",
      "totalJPY": 7740,
      "count": 1
    },
    {
      "date": "2026-04-11",
      "category": "clothing",
      "totalJPY": 6918,
      "count": 1
    },
    {
      "date": "2026-04-11",
      "category": "convenience-store",
      "totalJPY": 2159,
      "count": 3
    },
    {
      "date": "2026-04-11",
      "category": "general-shopping",
      "totalJPY": 58472,
      "count": 5
    },
    {
      "date": "2026-04-11",
      "category": "pharmacy-beauty",
      "totalJPY": 1078,
      "count": 1
    },
    {
      "date": "2026-04-11",
      "category": "souvenirs",
      "totalJPY": 5080,
      "count": 2
    }
  ],
  "excludedSummary": [
    {
      "classification": "transfer",
      "label": "Transfer",
      "totalJPY": 269663,
      "count": 6
    },
    {
      "classification": "exchange",
      "label": "Exchange",
      "totalJPY": 8754,
      "count": 47
    },
    {
      "classification": "reimbursed-payment",
      "label": "Reimbursed Payment",
      "totalJPY": 55960,
      "count": 2
    }
  ],
  "manualExpenses": [
    {
      "date": "2026-03-27",
      "startDate": "2026-03-27",
      "endDate": "2026-03-31",
      "description": "Hotel stay 27-31 Mar",
      "normalizedMerchant": "Hotel booking",
      "amountJPY": 95084,
      "category": "lodging",
      "classification": "manual-expense",
      "notes": "Accommodation booked outside the bank export.",
      "sourceAmount": 506.52,
      "sourceCurrency": "EUR",
      "sourceAmountJPY": 95084
    },
    {
      "date": "2026-03-31",
      "startDate": "2026-03-31",
      "endDate": "2026-04-03",
      "description": "Hotel stay 31 Mar-3 Apr",
      "normalizedMerchant": "Hotel booking",
      "amountJPY": 99351,
      "category": "lodging",
      "classification": "manual-expense",
      "notes": "Accommodation booked outside the bank export.",
      "sourceAmount": 529.25,
      "sourceCurrency": "EUR",
      "sourceAmountJPY": 99351
    },
    {
      "date": "2026-04-03",
      "startDate": "2026-04-03",
      "endDate": "2026-04-05",
      "description": "Hotel stay 3-5 Apr",
      "normalizedMerchant": "Hotel booking",
      "amountJPY": 102013,
      "category": "lodging",
      "classification": "manual-expense",
      "notes": "Accommodation booked outside the bank export.",
      "sourceAmount": 543.43,
      "sourceCurrency": "EUR",
      "sourceAmountJPY": 102013
    },
    {
      "date": "2026-04-05",
      "startDate": "2026-04-05",
      "endDate": "2026-04-07",
      "description": "Hotel stay 5-7 Apr",
      "normalizedMerchant": "Hotel booking",
      "amountJPY": 41862,
      "category": "lodging",
      "classification": "manual-expense",
      "notes": "Accommodation booked outside the bank export.",
      "sourceAmount": 223,
      "sourceCurrency": "EUR",
      "sourceAmountJPY": 41862
    },
    {
      "date": "2026-04-07",
      "startDate": "2026-04-07",
      "endDate": "2026-04-10",
      "description": "Hotel stay 7-10 Apr",
      "normalizedMerchant": "Hotel booking",
      "amountJPY": 53600,
      "category": "lodging",
      "classification": "manual-expense",
      "notes": "Accommodation booked outside the bank export.",
      "sourceAmount": 285.53,
      "sourceCurrency": "EUR",
      "sourceAmountJPY": 53600
    },
    {
      "date": "2026-04-10",
      "startDate": "2026-04-10",
      "endDate": "2026-04-12",
      "description": "Hotel stay 10-12 Apr",
      "normalizedMerchant": "Hotel booking",
      "amountJPY": 60795,
      "category": "lodging",
      "classification": "manual-expense",
      "notes": "Accommodation booked outside the bank export.",
      "sourceAmount": 323.86,
      "sourceCurrency": "EUR",
      "sourceAmountJPY": 60795
    },
    {
      "date": "2026-04-09",
      "startDate": "2026-04-09",
      "endDate": "2026-04-09",
      "description": "Klook paid tour",
      "normalizedMerchant": "Klook",
      "amountJPY": 28158,
      "category": "attractions",
      "classification": "manual-expense",
      "notes": "Paid tour booked via Klook.",
      "sourceAmount": 150,
      "sourceCurrency": "EUR",
      "sourceAmountJPY": 28158
    },
    {
      "date": "2026-03-26",
      "startDate": "2026-03-26",
      "endDate": "2026-03-26",
      "description": "Main round-trip flights Lisbon-Tokyo-Lisbon",
      "normalizedMerchant": "International flights",
      "amountJPY": 915090,
      "category": "flights",
      "classification": "manual-expense",
      "notes": "Main international flights: 26 Mar outbound, 12 Apr return.",
      "sourceAmount": 4874.76,
      "sourceCurrency": "EUR",
      "sourceAmountJPY": 915090
    },
    {
      "date": "2026-04-10",
      "startDate": "2026-04-10",
      "endDate": "2026-04-10",
      "description": "Internal flight Fukuoka-Tokyo",
      "normalizedMerchant": "Domestic flight",
      "amountJPY": 42791,
      "category": "flights",
      "classification": "manual-expense",
      "notes": "Internal flight from Fukuoka to Tokyo.",
      "sourceAmount": 227.95,
      "sourceCurrency": "EUR",
      "sourceAmountJPY": 42791
    }
  ],
  "reviewTransactions": []
}
